[{"countList":[10],"countRatiosList":[1],"desc":"可开出所有素材碎片","itemBooksList":[10001,10001,10001,10001,10001,10001,10001,10001,10001,10001],"itemBooksRatiosList":[1,1,1,1,1,1,1,1,1,1],"keyId":2060001,"name":"素材碎片宝箱"}, 
{"countList":[10],"countRatiosList":[1],"desc":"可开出所有素材","itemBooksList":[10002,10002,10002,10002,10002,10002,10002,10002,10002,10002],"itemBooksRatiosList":[1,1,1,1,1,1,1,1,1,1],"keyId":2060002,"name":"素材宝箱"}, 
{"countList":[10],"countRatiosList":[1],"desc":"可开出所有卷轴","itemBooksList":[10003,10003,10003,10003,10003,10003,10003,10003,10003,10003],"itemBooksRatiosList":[1,1,1,1,1,1,1,1,1,1],"keyId":2060003,"name":"卷轴宝箱"}, 
{"countList":[10],"countRatiosList":[1],"desc":"可开出所有典籍","itemBooksList":[10004,10004,10004,10004,10004,10004,10004,10004,10004,10004],"itemBooksRatiosList":[1,1,1,1,1,1,1,1,1,1],"keyId":2060004,"name":"典籍宝箱"}, 
{"countList":[10],"countRatiosList":[1],"desc":"可开出所有插件","itemBooksList":[10005,10005,10005,10005,10005,10005,10005,10005,10005,10005],"itemBooksRatiosList":[1,1,1,1,1,1,1,1,1,1],"keyId":2060005,"name":"插件宝箱"}, 
{"countList":[10],"countRatiosList":[1],"desc":"可开出说有普通道具","itemBooksList":[10006,10006,10006,10006,10006,10006,10006,10006,10006,10006],"itemBooksRatiosList":[1,1,1,1,1,1,1,1,1,1],"keyId":2060006,"name":"普通道具宝箱"}, 
{"countList":[6],"countRatiosList":[1],"desc":"可开出所有物品","itemBooksList":[19001,19002,19003,19004,19005,19006,19007],"itemBooksRatiosList":[1,1,1,1,1,1,1],"keyId":2999999,"name":"万能宝箱"}, 
{"countList":[1],"countRatiosList":[1],"desc":"可开出说有普通道具","itemBooksList":[12022],"itemBooksRatiosList":[1],"keyId":2111111,"name":"宝箱"}]